gicosf.py
dphoyes.gicosf-0.2.0.dist-info/DESCRIPTION.rst
dphoyes.gicosf-0.2.0.dist-info/METADATA
dphoyes.gicosf-0.2.0.dist-info/RECORD
dphoyes.gicosf-0.2.0.dist-info/WHEEL
dphoyes.gicosf-0.2.0.dist-info/entry_points.txt
dphoyes.gicosf-0.2.0.dist-info/metadata.json
dphoyes.gicosf-0.2.0.dist-info/top_level.txt
