Metadata-Version: 2.0
Name: dphoyes.gicosf
Version: 0.2.0
Summary: Tool for deploying Symfony projects over sftp
Home-page: https://github.com/dphoyes/gicosf
Author: David Hoyes
Author-email: dphoyes@gmail.com
License: MIT
Download-URL: https://github.com/dphoyes/gicosf/archive/v0.2.0.tar.gz
Keywords: git composer sftp symfony dandelion deployment
Platform: UNKNOWN
Classifier: Development Status :: 4 - Beta
Classifier: Intended Audience :: Developers
Classifier: License :: OSI Approved :: MIT License
Classifier: Programming Language :: Python :: 3.5
Classifier: Programming Language :: Python :: 3.6
Classifier: Programming Language :: Python :: 3 :: Only
Requires-Dist: argcomplete
Requires-Dist: dphoyes.libssh2
Requires-Dist: paramiko
Requires-Dist: pyyaml
